{
  "@context": "https://schema.org",
  "generated_at": "2026-06-24T10:28:26.763Z",
  "base_url": "https://example.com",
  "currency": "ILS",
  "count": 5,
  "products": [
    {
      "id": "6459e406-0e86-4561-a277-a459d463136d",
      "slug": "avgyvt-mvshchtvtkrambl-kvkyz-wdfqee",
      "name": "עוגיות מושחתות~״קראמבל קוקיז״",
      "name_translations": {},
      "description": "",
      "short_description": "עוגיות מושחתות בטעמים לבחירה:\nקינדר,אוראו,פיסטוק,אמסטרדם,סוכריות צבעוניות,נוטלה,שוקולד צ׳יפס,סמורס,ריסס.\nמחיר לעוגיה 1: 15₪",
      "sku": null,
      "brand": null,
      "price": 15,
      "base_price": 15,
      "sale_price": null,
      "currency": "ILS",
      "images": [
        "https://example.com/assets/product-enhanced-1782243118083-e5e8p.webp",
        "https://example.com/assets/product-enhanced-1782243145099-as2bjo.webp"
      ],
      "in_stock": true,
      "stock_status": "in_stock",
      "url": "https://example.com/product/avgyvt-mvshchtvtkrambl-kvkyz-wdfqee",
      "categories": [],
      "updated_at": "2026-06-24T10:19:09.634Z"
    },
    {
      "id": "c8c757a3-10a2-4a39-8ac9-f38cf98a1037",
      "slug": "avgt-bntv-mavtsbt-kw4unt",
      "name": "עוגת בנטו מעוצבת ",
      "name_translations": {},
      "description": "",
      "short_description": "עוגת בנטו בטעם שוקולד/וניל עם מילוי לבחירה ועיצוב בהתאמה אישית. \n•במקרה של עיצוב מיוחד שכולל דף סוכר/אלמנטים תיהיה תוספת תשלום. \n",
      "sku": null,
      "brand": null,
      "price": 95,
      "base_price": 95,
      "sale_price": null,
      "currency": "ILS",
      "images": [
        "https://example.com/assets/product-enhanced-1782242410649-obrseg.webp",
        "https://example.com/assets/product-enhanced-1782242383965-df8js4.webp"
      ],
      "in_stock": true,
      "stock_status": "in_stock",
      "url": "https://example.com/product/avgt-bntv-mavtsbt-kw4unt",
      "categories": [],
      "updated_at": "2026-06-23T19:21:02.042Z"
    },
    {
      "id": "99c589f9-a038-404b-ad80-7875e066081f",
      "slug": "avgvt-gbynh-myvchdvt-kvtr-22-z24za0",
      "name": "עוגות גבינה מיוחדות- קוטר 22",
      "name_translations": {},
      "description": "",
      "short_description": "עוגות גבינה עשירות ~ קוטר 22\nמספיקות ל10 אנשים\nמגיעות עם פירות העונה,ריבות וקרמים מיוחדים \nטווח מחירים: 95₪-115₪",
      "sku": null,
      "brand": null,
      "price": 95,
      "base_price": 95,
      "sale_price": null,
      "currency": "ILS",
      "images": [
        "https://example.com/assets/product-enhanced-1782241728522-lql16c.webp",
        "https://example.com/assets/product-enhanced-1782241913188-hla794.webp",
        "https://example.com/assets/product-enhanced-1782241995975-1n3uo.webp"
      ],
      "in_stock": true,
      "stock_status": "in_stock",
      "url": "https://example.com/product/avgvt-gbynh-myvchdvt-kvtr-22-z24za0",
      "categories": [],
      "updated_at": "2026-06-23T19:13:41.352Z"
    },
    {
      "id": "d6df8ebf-8a82-4d05-a340-11e9d7dde97e",
      "slug": "avgt-gbynh-apvyh-kvtr-18-oi3fp7",
      "name": "עוגת גבינה אפויה - קוטר 18",
      "name_translations": {},
      "description": "",
      "short_description": "עוגת גבינה עשירה קוטר 18, העוגה מתאימה ל6-8 אנשים \nומגיעה עם אבקת סוכר מעל.\n85₪",
      "sku": null,
      "brand": null,
      "price": 85,
      "base_price": 85,
      "sale_price": null,
      "currency": "ILS",
      "images": [
        "https://example.com/assets/product-enhanced-1782241360787-3c6akb.webp",
        "https://example.com/assets/product-ai-fit-1782241330550-npxe8i.webp"
      ],
      "in_stock": true,
      "stock_status": "in_stock",
      "url": "https://example.com/product/avgt-gbynh-apvyh-kvtr-18-oi3fp7",
      "categories": [],
      "updated_at": "2026-06-23T19:04:08.744Z"
    },
    {
      "id": "64561b36-ec3c-4137-905f-631108d33d6b",
      "slug": "synbvn-kynmvn-am-glyyz-o9hdsl",
      "name": "סינבון קינמון עם גלייז ",
      "name_translations": {},
      "description": "",
      "short_description": "סינבון חלביים רכים ואווריריים שמגיעים עם גלייז שמנת מעל,הסינבון מגיע בכמה גדלים:\n3/4/6/8\nטווח מחירים: \n40₪-100₪",
      "sku": null,
      "brand": null,
      "price": 40,
      "base_price": 40,
      "sale_price": null,
      "currency": "ILS",
      "images": [
        "https://example.com/assets/product-enhanced-1782240206956-xld8d9.webp",
        "https://example.com/assets/product-enhanced-1782240174218-3vpyn.webp"
      ],
      "in_stock": true,
      "stock_status": "in_stock",
      "url": "https://example.com/product/synbvn-kynmvn-am-glyyz-o9hdsl",
      "categories": [],
      "updated_at": "2026-06-23T18:50:29.636Z"
    }
  ]
}